basebio/__init__.py
basebio/main.py
basebio/modules/__init__.py
basebio/modules/cmd.py
basebio/modules/crud.py
basebio/modules/nbib2bib.py
basebio/modules/prepare.py
basebio/utils/cmdtools.py
basebio/utils/cutadapt.py
basebio/utils/db.py
basebio/utils/env.py
basebio/utils/minimap2.py
basebio/utils/nbib2bib.py
basebio/utils/prepare.py
basebio/utils/reference.py
basebio-0.4.8.dist-info/METADATA
basebio-0.4.8.dist-info/WHEEL
basebio-0.4.8.dist-info/entry_points.txt
basebio-0.4.8.dist-info/RECORD
