Metadata-Version: 2.3
Name: basebio
Version: 0.4.8
Summary: 
Author: DeYing Zhang
Author-email: legendzdy@dingtalk.com
Requires-Python: >=3.10
Classifier: Programming Language :: Python :: 3
Classifier: Programming Language :: Python :: 3.10
Classifier: Programming Language :: Python :: 3.11
Classifier: Programming Language :: Python :: 3.12
Classifier: Programming Language :: Python :: 3.13
Requires-Dist: pyyaml (>=6.0.2)
Requires-Dist: retrying (>=1.3.4)
Requires-Dist: sqlalchemy (>=2.0.40)
Requires-Dist: typer (>=0.15.2)
